.hgignore
.hgtags
CHANGES.txt
README.txt
pytest.ini
setup.cfg
setup.py
docs/conf.py
docs/history.rst
docs/index.rst
examples/echo.py
examples/ns.py
examples/tests.py
examples/thread.py
examples/timer.py
examples/http/cherrypy_wsgi.py
examples/http/client.py
examples/http/heads.py
examples/http/reqline.py
examples/http/server.py
examples/http/server_chunked.py
examples/http/server_ooo.py
examples/http/server_wsgi.py
examples/http/tests.py
yg/__init__.py
yg.eventful.egg-info/PKG-INFO
yg.eventful.egg-info/SOURCES.txt
yg.eventful.egg-info/dependency_links.txt
yg.eventful.egg-info/namespace_packages.txt
yg.eventful.egg-info/requires.txt
yg.eventful.egg-info/top_level.txt
yg/eventful/__init__.py
yg/eventful/app.py
yg/eventful/defer.py
yg/eventful/eventbase.py
yg/eventful/logmod.py
yg/eventful/mixins.py
yg/eventful/pipeline.py
yg/eventful/protocol.py
yg/eventful/timers.py
yg/eventful/util.py
yg/eventful/proto/__init__.py
yg/eventful/proto/http.py
yg/eventful/proto/netstring.py