Metadata-Version: 1.1
Name: yg.eventful
Version: 2.1
Summary: A library to facilitate pyevent stuff
Home-page: https://github.com/yougov/yg.eventful
Author: Jamie Turner
Author-email: dev@yougov.com
License: UNKNOWN
Platform: UNKNOWN
Classifier: Development Status :: 5 - Production/Stable
Classifier: Intended Audience :: Developers
Classifier: License :: OSI Approved :: MIT License
Classifier: Programming Language :: Python :: 2.7
